LICENSE
MANIFEST.in
README.md
setup.py
gan_lab/__init__.py
gan_lab/_int.py
gan_lab/config.py
gan_lab/data_config.py
gan_lab/train.py
gan_lab.egg-info/PKG-INFO
gan_lab.egg-info/SOURCES.txt
gan_lab.egg-info/dependency_links.txt
gan_lab.egg-info/not-zip-safe
gan_lab.egg-info/requires.txt
gan_lab.egg-info/top_level.txt
gan_lab/progan/__init__.py
gan_lab/progan/architectures.py
gan_lab/progan/base.py
gan_lab/progan/learner.py
gan_lab/resnetgan/__init__.py
gan_lab/resnetgan/architectures.py
gan_lab/resnetgan/base.py
gan_lab/resnetgan/learner.py
gan_lab/resnetgan/resblocks.py
gan_lab/stylegan/__init__.py
gan_lab/stylegan/architectures.py
gan_lab/stylegan/base.py
gan_lab/stylegan/learner.py
gan_lab/utils/__init__.py
gan_lab/utils/backprop_utils.py
gan_lab/utils/custom_layers.py
gan_lab/utils/data_utils.py
gan_lab/utils/initializer.py
gan_lab/utils/latent_utils.py