Metadata-Version: 2.1
Name: gan-lab
Version: 0.3.0
Summary: StyleGAN, ProGAN, and ResNet GANs to experiment with
Home-page: https://github.com/sidward14/gan-lab
Author: Sidhartha Parhi
Author-email: sidhartha.parhi@gmail.com
License: UNKNOWN
Keywords: GAN GAN-Zoo ML generative neural model
Platform: UNKNOWN
Requires-Python: >= 3.6
